Workbook

Sheet Summary
A1: Three-year revenue CAGR - summary
A3: Company | B3: Projection period | C3: 3-year revenue CAGR | D3: Basis
A4: Rubrik | B4: FY2027-FY2030 | C4: =Rubrik!C10 -> 0.22550637 | D4: ARR growth-decay model, converted to revenue
A5: Varonis | B5: FY2026-FY2029 | C5: =Varonis!C11 -> 0.19073196 | D5: Revenue growth-decay model
A6: Commvault | B6: FY2027-FY2030 | C6: =Commvault!C12 -> 0.1024846 | D6: Flat guided growth
A8: Fiscal years differ across companies; periods are not calendar-aligned.
A10: Academic exercise. Not investment advice. Figures sourced from public filings as of August 2026; revised October 2026.

Sheet Assumptions
A1: Data Security Sector - Revenue Projection Model
A2: All figures USD millions. Blue = input. Black = formula.
A4: Shared assumptions
A5: Terminal growth rate | B5: 0.1712 | C5: Mordor Intelligence data security market CAGR (CY2026-CY2031); flat-share assumption
A6: Decay factor (k) | B6: =ROUND(B38,2) -> 0.75 | C6: Rubrik filed exit subscription ARR, FY2024 to FY2026 (rows 30 to 38): 16.70pp / 22.24pp = 0.751
A9: Company inputs
A10: Rubrik
A11: FY2026 exit subscription ARR | B11: 1462.092 | C11: Q4 FY2026 earnings release: $1,462,092k
A12: FY2026 revenue | B12: 1316.191 | C12: FY2026 10-K income statement: $1,316,191k
A13: FY2027 exit subscription ARR (guidance midpoint) | B13: 1834 | C13: Q4 FY2026 earnings release, $1,829-1,839m
A14: FY2027 revenue (guidance midpoint) | B14: 1602 | C14: Q4 FY2026 earnings release, $1,597-1,607m
A15: Revenue / average-ARR ratio | B15: =ROUND(B39,2) -> 0.97 | C15: Calibrated to FY2027 guidance (row 39)
A17: Varonis
A18: FY2024 revenue | B18: 550.95 | C18: FY2025 10-K: $550,950k
A19: FY2025 revenue | B19: 623.532 | C19: FY2025 10-K: $623,532k
A20: FY2026 revenue (guidance midpoint) | B20: 737 | C20: Q2 2026 earnings release, $735-739m
A21: FY2026 base growth (SaaS ARR ex-conversions) | B21: 0.205 | C21: Q2 2026 earnings release, guided 20-21%
A23: Commvault
A24: FY2024 revenue | B24: 839.247 | C24: Q4 FY2024 earnings release: $839,247k
A25: FY2025 revenue | B25: 995.619 | C25: Q4 FY2026 earnings release: $995,619k
A26: FY2026 revenue | B26: 1183.69 | C26: Q4 FY2026 earnings release: $1,183,690k
A27: FY2027 revenue (guidance midpoint) | B27: 1305 | C27: Q4 FY2026 earnings release, $1,300-1,310m
A29: Rubrik history (decay factor and ratio derivation)
A30: FY2024 exit subscription ARR | B30: 784.029 | C30: Q4 FY2025 earnings release (8-K Ex. 99.1): $784,029k
A31: FY2025 exit subscription ARR | B31: 1092.584 | C31: Q4 FY2026 earnings release: $1,092,584k
A32: FY2025 revenue | B32: 886.544 | C32: FY2026 10-K income statement: $886,544k
A33: FY2025 subscription ARR growth | B33: =B31/B30-1 -> 0.39355049
A34: FY2026 subscription ARR growth | B34: =B11/B31-1 -> 0.33819642
A35: FY2026 revenue growth | B35: =B12/B32-1 -> 0.48463133 | C35: Inflated by material rights
A36: FY2025 gap above terminal growth | B36: =B33-B5 -> 0.22235049
A37: FY2026 gap above terminal growth | B37: =B34-B5 -> 0.16699642
A38: Decay factor, unrounded (FY2026 gap / FY2025 gap) | B38: =B37/B36 -> 0.75105038 | C38: B6 rounds this to two decimals
A39: FY2027 revenue / average FY2027 ARR, unrounded | B39: =B14/((B11+B13)/2) -> 0.97206025 | C39: B15 rounds this to two decimals
A42: Method
A43: ARR growth in year t = terminal + (base growth - terminal) x k^t
A44: Revenue (Rubrik) = ratio x (opening ARR + closing ARR) / 2
A45: Commvault: growth held flat, as guided growth is already below the terminal rate

Sheet Rubrik
A1: Rubrik (NASDAQ: RBRK) - fiscal year ends 31 January
A3: FY | B3: Basis | C3: Exit subscription ARR | D3: ARR growth | E3: Revenue | F3: Revenue growth
A4: FY26 | B4: Reported | C4: =Assumptions!$B$11 -> 1462.092 | D4: =Assumptions!$B$34 -> 0.33819642 | E4: =Assumptions!$B$12 -> 1316.191 | F4: =Assumptions!$B$35 -> 0.48463133
A5: FY27 | B5: Company guidance | C5: =Assumptions!$B$13 -> 1834 | D5: =C5/C4-1 -> 0.25436703 | E5: =Assumptions!$B$14 -> 1602 | F5: =E5/E4-1 -> 0.21714857
A6: FY28 | B6: Projected | C6: =C5*(1+D6) -> 2262.3771 | D6: =Assumptions!$B$5+($D$5-Assumptions!$B$5)*Assumptions!$B$6^1 -> 0.23357527 | E6: =Assumptions!$B$15*(C5+C6)/2 -> 1986.7429 | F6: =E6/E5-1 -> 0.24016409
A7: FY29 | B7: Projected | C7: =C6*(1+D7) -> 2755.5333 | D7: =Assumptions!$B$5+($D$5-Assumptions!$B$5)*Assumptions!$B$6^2 -> 0.21798145 | E7: =Assumptions!$B$15*(C6+C7)/2 -> 2433.6865 | F7: =E7/E6-1 -> 0.224963
A8: FY30 | B8: Projected | C8: =C7*(1+D8) -> 3323.9615 | D8: =Assumptions!$B$5+($D$5-Assumptions!$B$5)*Assumptions!$B$6^3 -> 0.20628609 | E8: =Assumptions!$B$15*(C7+C8)/2 -> 2948.555 | F8: =E8/E7-1 -> 0.21155907
A10: 3-year revenue CAGR (FY27-FY30) | C10: =(E8/E5)^(1/3)-1 -> 0.22550637
A12: Benchmark - FY30 exit ARR
A13: Constant FY26 growth held | C13: =Assumptions!$B$13*(1+$D$4)^3 -> 4395.0005
A14: Constant FY27 growth held | C14: =Assumptions!$B$13*(1+$D$5)^3 -> 3619.7054
A15: This model | C15: =C8 -> 3323.9615
A16: Market growth only, flat share | C16: =Assumptions!$B$13*(1+Assumptions!$B$5)^3 -> 2946.4055

Sheet Varonis
A1: Varonis (NASDAQ: VRNS) - fiscal year ends 31 December
A3: FY | B3: Basis | C3: Revenue | D3: Revenue growth
A4: FY24 | B4: Reported | C4: =Assumptions!$B$18 -> 550.95
A5: FY25 | B5: Reported | C5: =Assumptions!$B$19 -> 623.532 | D5: =C5/C4-1 -> 0.13173972
A6: FY26 | B6: Company guidance | C6: =Assumptions!$B$20 -> 737 | D6: =C6/C5-1 -> 0.18197623
A7: FY27 | B7: Projected | C7: =C6*(1+D7) -> 881.85735 | D7: =Assumptions!$B$5+(Assumptions!$B$21-Assumptions!$B$5)*Assumptions!$B$6^1 -> 0.19655
A8: FY28 | B8: Projected | C8: =C7*(1+D8) -> 1049.5976 | D8: =Assumptions!$B$5+(Assumptions!$B$21-Assumptions!$B$5)*Assumptions!$B$6^2 -> 0.1902125
A9: FY29 | B9: Projected | C9: =C8*(1+D9) -> 1244.2554 | D9: =Assumptions!$B$5+(Assumptions!$B$21-Assumptions!$B$5)*Assumptions!$B$6^3 -> 0.18545938
A11: 3-year revenue CAGR (FY2026-FY2029) | C11: =(C9/C6)^(1/3)-1 -> 0.19073196

Sheet Commvault
A1: Commvault (NASDAQ: CVLT) - fiscal year ends 31 March
A3: FY | B3: Basis | C3: Revenue | D3: Revenue growth
A4: FY24 | B4: Reported | C4: =Assumptions!$B$24 -> 839.247
A5: FY25 | B5: Reported | C5: =Assumptions!$B$25 -> 995.619 | D5: =C5/C4-1 -> 0.18632417
A6: FY26 | B6: Reported | C6: =Assumptions!$B$26 -> 1183.69 | D6: =C6/C5-1 -> 0.18889856
A7: FY27 | B7: Company guidance | C7: =Assumptions!$B$27 -> 1305 | D7: =C7/C6-1 -> 0.1024846
A8: FY28 | B8: Projected | C8: =C7*(1+D8) -> 1438.7424 | D8: =$D$7 -> 0.1024846
A9: FY29 | B9: Projected | C9: =C8*(1+D9) -> 1586.1914 | D9: =$D$7 -> 0.1024846
A10: FY30 | B10: Projected | C10: =C9*(1+D10) -> 1748.7515 | D10: =$D$7 -> 0.1024846
A12: 3-year revenue CAGR (FY27-FY30) | C12: =(C10/C7)^(1/3)-1 -> 0.1024846
A14: Growth held flat, guided FY27 growth is below the terminal market rate, so the decay framework does not apply.
