Workbook

Sheet Guide
A1: Rubrik (RBRK): three-statement model and DCF
A2: Academic exercise. Not investment advice. Source data: Rubrik FY2026 Form 10-K and FY2027 Q2 earnings release.
A4: How the model flows
A5: 1. Assumptions: every input lives here. Blue = typed input, yellow = key judgement or a value you should update.
A6: 2. Model: revenue build, then income statement, balance sheet and cash flow, FY2024A to FY2031E.
A7: Revenue comes from the subscription ARR growth-decay curve. Costs and working capital are % of revenue.
A8: The cash flow statement is built from balance sheet changes; closing cash feeds back into the balance sheet.
A9: 3. DCF: unlevered free cash flow from the Model for FY2027E to FY2031E, a five-year fade to FY2036E, then a terminal value.
A10: 4. Checks: balance sheet balance, ties to filed numbers, guidance reconciliation, and a backtest of the working-capital method.
A11: 5. Reconciliation: bridges the data security sector report's Rubrik revenue projection to this model, one input at a time.
A13: Colour code
A14: Blue text = hardcoded input (historical filed figures or assumptions). Black = formula. Green = link from another sheet.
... A20: Update the yellow DCF inputs on the Assumptions sheet: risk-free rate, beta, current share price, and years elapsed.

Sheet Assumptions
A1: Rubrik (RBRK): assumptions
A2: $ millions unless stated. Blue = input. Yellow = key judgement or value to update. Notes give the source or basis.
A4: Single-value inputs | B4: Value | C4: Source / basis
A5: FY2026 exit subscription ARR | B5: 1462.092 | C5: Q4 FY2026 earnings release: $1,462,092k
A6: FY2027 exit subscription ARR, guidance midpoint | B6: 1882.5 | C6: Q2 FY2027 release: $1,880m to $1,885m
A7: FY2027 revenue, guidance midpoint | B7: 1689 | C7: Q2 FY2027 release: $1,685m to $1,693m
A8: Market growth rate (decay floor) | B8: 0.1712 | C8: Mordor Intelligence data security CAGR; growth above this = share gain
A9: Decay factor k | B9: =ROUND((Model!D7-B8)/(Model!C7-B8),2) | C9: Formula: FY2026 gap above market growth / FY2025 gap, from filed exit ARR FY2024 to FY2026 (Model row 7), rounded. 16.70pp / 22.24pp = 0.751
A10: Revenue / average ARR, FY2028E onward | B10: 1 | C10: FY2027 implies about 1.01 incl. residual material rights; about 1.00 excluding them
A11: Accounts receivable days (DSO) | B11: 70 | C11: FY2026 year-end 71 days; FY2025 73 days
A12: Deferred commissions, current (% revenue) | B12: 0.08 | C12: FY2026: 8.4%
A13: Deferred commissions, noncurrent (% revenue) | B13: 0.115 | C13: FY2026: 12.0%
A14: Prepaid and other current assets (% revenue) | B14: 0.11 | C14: FY2026: 13.7%; lower by Jul 2026
A15: Accounts payable (% revenue) | B15: 0.011 | C15: FY2026: 1.2%
A16: Accrued and other current liabilities (% revenue) | B16: 0.15 | C16: FY2026: 17.5%; lower by Jul 2026
A17: Deferred revenue: current share of total | B17: 0.6 | C17: FY2026: 58%; Jul 2026: 61%
A18: Interest yield on opening cash and investments | B18: 0.035 | C18: FY2026 about 4.4%; H1 FY2027 annualised about 3.8%. Opening balance avoids a circular reference
A19: Convertible notes, face value | B19: 1150 | C19: 0.00% convertible senior notes due 2030
A20: Annual accretion of note discount | B20: 4.4 | C20: Carrying value rose $2.2m in H1 FY2027
A22: Per-year drivers | C22: Source / basis | E22: FY2027E | F22: FY2028E | G22: FY2029E | H22: FY2030E | I22: FY2031E
A23: Cost of revenue (% revenue) | C23: FY2026: 19.9%; H1 FY2027: 20.6% | E23: 0.205 | F23: 0.205 | G23: 0.205 | H23: 0.205 | I23: 0.205
A24: Research and development (% revenue) | C24: FY2026: 28.4%; H1 FY2027: 29.6% | E24: 0.295 | F24: 0.28 | G24: 0.265 | H24: 0.25 | I24: 0.24
A25: Sales and marketing (% revenue) | C25: FY2026: 58.4%; H1 FY2027: 51.3% | E25: 0.52 | F25: 0.48 | G25: 0.445 | H25: 0.415 | I25: 0.39
A26: General and administrative (% revenue) | C26: FY2026: 19.5%; H1 FY2027: 13.8% | E26: 0.14 | F26: 0.125 | G26: 0.115 | H26: 0.105 | I26: 0.1
A27: Stock-based compensation (% revenue, memo) | C27: Already inside the cost lines above. FY2026: 25.0%; H1 FY2027: 21.4% | E27: 0.21 | F27: 0.19 | G27: 0.17 | H27: 0.155 | I27: 0.14
A28: Depreciation (% revenue) | C28: PP&E and capitalised software | E28: 0.023 | F28: 0.023 | G28: 0.023 | H28: 0.023 | I28: 0.023
A29: Amortisation of acquired intangibles ($m) | C29: Trailing twelve months to Jul 2026: $11.3m | E29: 11 | F29: 11 | G29: 11 | H29: 11 | I29: 11
A30: Capex incl. capitalised software (% revenue) | C30: FY2026: 3.4%; H1 FY2027: 2.4% | E30: 0.026 | F30: 0.026 | G30: 0.026 | H30: 0.026 | I30: 0.026
A31: Cash taxes (% revenue) | C31: Mostly foreign; $1.35bn of US federal NOLs | E31: 0.012 | F31: 0.012 | G31: 0.012 | H31: 0.012 | I31: 0.012
A32: Deferred revenue, total (% revenue) | C32: FY2025: 160%; FY2026: 140%. FY2027 calibrated to FCF guidance (see Checks) | E32: 1.274 | F32: 1.25 | G32: 1.23 | H32: 1.22 | I32: 1.21
A33: Acquisitions ($m) | C33: Strata.io in FY2027; goodwill $199.6m to $223.2m | E33: 23.591 | F33: 0 | G33: 0 | H33: 0 | I33: 0
A35: DCF inputs
A36: Valuation date | B36: 31 Jan 2026 | C36: Last audited balance sheet; model base
A37: Risk-free rate | B37: 0.052 | C37: US 10-year Treasury yield, about 5.2% at 13 Oct 2026 close. Update when re-valuing
A38: Equity risk premium | B38: 0.045 | C38: Damodaran implied ERP is typically 4% to 5%; update if desired
A39: Levered beta | B39: 1.25 | C39: Top of Rubrik's published range (1.12 to 1.24, Oct 2026); Commvault 0.82. Under three years of trading history, so treated as a judgement
A40: Cost of equity (CAPM) | B40: =B37+B39*B38 | C40: Risk-free + beta x equity risk premium
A41: Pre-tax cost of debt | B41: 0.05 | C41: 0% coupon understates the economic cost because of the conversion option
A42: Tax rate applied to debt | B42: 0 | C42: No cash tax shield while NOLs are being used
A43: Share price ($), for weights and comparison | B43: 118.47 | C43: RBRK close, 13 Oct 2026. Update when re-valuing
A44: Basic shares outstanding (m) | B44: 202.242 | C44: Class A 157.37m + Class B 44.87m, 31 Jan 2026
A45: Market value of equity | B45: =B43*B44
A46: Debt at face | B46: =B19
A47: WACC | B47: =B45/(B45+B46)*B40+B46/(B45+B46)*B41*(1-B42) | C47: Market-value weights
A48: Terminal (perpetuity) growth | B48: 0.04 | C48: Must sit below WACC; long-run nominal growth
A49: Steady-state UFCF margin at end of fade | B49: 0.18 | C49: Judgement. SBC treated as a cost, so this is after SBC
A50: Diluted shares excluding convertible (m) | B50: 214.4 | C50: Q4 FY2026 non-GAAP diluted 223.6m less 9.2m from the notes
A51: Years from valuation date to today | B51: 0.7 | C51: 31 Jan 2026 to 13 Oct 2026 (255 days)

Sheet Model
A1: Rubrik (RBRK): integrated three-statement model
A2: $ millions. Fiscal year ends 31 January. A = reported (SEC filings), E = projected.
B3: FY2024A | C3: FY2025A | D3: FY2026A | E3: FY2027E | F3: FY2028E | G3: FY2029E | H3: FY2030E | I3: FY2031E
A5: REVENUE BUILD
A6: Exit subscription ARR | B6: 784.029 | C6: 1092.584 | D6: =Assumptions!B5 | E6: =Assumptions!B6 | F6: =E6*(1+F7) | G6: =F6*(1+G7) | H6: =G6*(1+H7) | I6: =H6*(1+I7)
A7: Subscription ARR growth | C7: =C6/B6-1 | D7: =D6/C6-1 | E7: =E6/D6-1 | F7: =Assumptions!$B$8+($E$7-Assumptions!$B$8)*Assumptions!$B$9^F8 | G7: =Assumptions!$B$8+($E$7-Assumptions!$B$8)*Assumptions!$B$9^G8 | H7: =Assumptions!$B$8+($E$7-Assumptions!$B$8)*Assumptions!$B$9^H8 | I7: =Assumptions!$B$8+($E$7-Assumptions!$B$8)*Assumptions!$B$9^I8
A8: Decay step (years after FY2027) | E8: 0 | F8: 1 | G8: 2 | H8: 3 | I8: 4
A9: Average subscription ARR (opening + closing) / 2 | E9: =(D6+E6)/2 | F9: =(E6+F6)/2 | G9: =(F6+G6)/2 | H9: =(G6+H6)/2 | I9: =(H6+I6)/2
A10: Revenue / average ARR | E10: =E12/E9 | F10: =Assumptions!$B$10 | G10: =Assumptions!$B$10 | H10: =Assumptions!$B$10 | I10: =Assumptions!$B$10
A11: INCOME STATEMENT
A12: Revenue | B12: 627.892 | C12: 886.544 | D12: 1316.191 | E12: =Assumptions!B7 | F12: =F9*F10 | G12: =G9*G10 | H12: =H9*H10 | I12: =I9*I10
A13: Revenue growth | C13: =C12/B12-1 | D13: =D12/C12-1 | E13: =E12/D12-1 | F13: =F12/E12-1 | G13: =G12/F12-1 | H13: =H12/G12-1 | I13: =I12/H12-1
A14: Cost of revenue | B14: 144.962 | C14: 265.748 | D14: 261.877 | E14: =E12*Assumptions!E23 | F14: =F12*Assumptions!F23 | G14: =G12*Assumptions!G23 | H14: =H12*Assumptions!H23 | I14: =I12*Assumptions!I23
A15: Gross profit | B15: =B12-B14 | C15: =C12-C14 | D15: =D12-D14 | E15: =E12-E14 | F15: =F12-F14 | G15: =G12-G14 | H15: =H12-H14 | I15: =I12-I14
A16: Gross margin | B16: =B15/B12 | C16: =C15/C12 | D16: =D15/D12 | E16: =E15/E12 | F16: =F15/F12 | G16: =G15/G12 | H16: =H15/H12 | I16: =I15/I12
A17: Research and development | B17: 206.527 | C17: 531.615 | D17: 373.682 | E17: =E12*Assumptions!E24 | F17: =F12*Assumptions!F24 | G17: =G12*Assumptions!G24 | H17: =H12*Assumptions!H24 | I17: =I12*Assumptions!I24
A18: Sales and marketing | B18: 482.532 | C18: 867.518 | D18: 769.019 | E18: =E12*Assumptions!E25 | F18: =F12*Assumptions!F25 | G18: =G12*Assumptions!G25 | H18: =H12*Assumptions!H25 | I18: =I12*Assumptions!I25
A19: General and administrative | B19: 100.377 | C19: 355.695 | D19: 257.029 | E19: =E12*Assumptions!E26 | F19: =F12*Assumptions!F26 | G19: =G12*Assumptions!G26 | H19: =H12*Assumptions!H26 | I19: =I12*Assumptions!I26
A20: Total operating expenses | B20: =SUM(B17:B19) | C20: =SUM(C17:C19) | D20: =SUM(D17:D19) | E20: =SUM(E17:E19) | F20: =SUM(F17:F19) | G20: =SUM(G17:G19) | H20: =SUM(H17:H19) | I20: =SUM(I17:I19)
A21: Operating income (EBIT) | B21: =B15-B20 | C21: =C15-C20 | D21: =D15-D20 | E21: =E15-E20 | F21: =F15-F20 | G21: =G15-G20 | H21: =H15-H20 | I21: =I15-I20
A22: Operating margin | B22: =B21/B12 | C22: =C21/C12 | D22: =D21/D12 | E22: =E21/E12 | F22: =F21/F12 | G22: =G21/G12 | H22: =H21/H12 | I22: =I21/I12
A23: Interest income | B23: 11.216 | C23: 25.353 | D23: 52.157 | E23: =(D34+D35)*Assumptions!$B$18 | F23: =(E34+E35)*Assumptions!$B$18 | G23: =(F34+F35)*Assumptions!$B$18 | H23: =(G34+G35)*Assumptions!$B$18 | I23: =(H34+H35)*Assumptions!$B$18
A24: Interest expense | B24: -30.295 | C24: -41.253 | D24: -17.227 | E24: =-(E52-D52) | F24: =-(F52-E52) | G24: =-(G52-F52) | H24: =-(H52-G52) | I24: =-(I52-H52)
A25: Other income / (expense), incl. debt extinguishment | B25: -1.884 | C25: 1.48 | D25: -15.987 | E25: 0 | F25: 0 | G25: 0 | H25: 0 | I25: 0
A26: Pre-tax income | B26: =B21+B23+B24+B25 | C26: =C21+C23+C24+C25 | D26: =D21+D23+D24+D25 | E26: =E21+E23+E24+E25 | F26: =F21+F23+F24+F25 | G26: =G21+G23+G24+G25 | H26: =H21+H23+H24+H25 | I26: =I21+I23+I24+I25
A27: Income tax expense | B27: 26.689 | C27: 6.368 | D27: 22.355 | E27: =E12*Assumptions!E31 | F27: =F12*Assumptions!F31 | G27: =G12*Assumptions!G31 | H27: =H12*Assumptions!H31 | I27: =I12*Assumptions!I31
A28: Net income | B28: =B26-B27 | C28: =C26-C27 | D28: =D26-D27 | E28: =E26-E27 | F28: =F26-F27 | G28: =G26-G27 | H28: =H26-H27 | I28: =I26-I27
A29: Memo: stock-based compensation (inside costs above) | B29: 5.715 | C29: 913.913 | D29: 329.374 | E29: =E12*Assumptions!E27 | F29: =F12*Assumptions!F27 | G29: =G12*Assumptions!G27 | H29: =H12*Assumptions!H27 | I29: =I12*Assumptions!I27
A30: Memo: depreciation and amortisation | B30: 24.305 | C30: 28.868 | D30: 37.115 | E30: =E12*Assumptions!E28+Assumptions!E29 | F30: =F12*Assumptions!F28+Assumptions!F29 | G30: =G12*Assumptions!G28+Assumptions!G29 | H30: =H12*Assumptions!H28+Assumptions!H29 | I30: =I12*Assumptions!I28+Assumptions!I29
A31: Memo: EBIT excluding SBC | B31: =B21+B29 | C31: =C21+C29 | D31: =D21+D29 | E31: =E21+E29 | F31: =F21+F29 | G31: =G21+G29 | H31: =H21+H29 | I31: =I21+I29
A33: BALANCE SHEET
A34: Cash and cash equivalents | C34: 186.331 | D34: 380.196 | E34: =E87 | F34: =F87 | G34: =G87 | H34: =H87 | I34: =I87
A35: Short-term investments | C35: 518.813 | D35: 1295.579 | E35: =D35 | F35: =E35 | G35: =F35 | H35: =G35 | I35: =H35
A36: Accounts receivable | C36: 177.627 | D36: 256.773 | E36: =E12*Assumptions!$B$11/365 | F36: =F12*Assumptions!$B$11/365 | G36: =G12*Assumptions!$B$11/365 | H36: =H12*Assumptions!$B$11/365 | I36: =I12*Assumptions!$B$11/365
A37: Deferred commissions, current | C37: 91.919 | D37: 110.651 | E37: =E12*Assumptions!$B$12 | F37: =F12*Assumptions!$B$12 | G37: =G12*Assumptions!$B$12 | H37: =H12*Assumptions!$B$12 | I37: =I12*Assumptions!$B$12
A38: Prepaid and other current assets | C38: 102.951 | D38: 180.365 | E38: =E12*Assumptions!$B$14 | F38: =F12*Assumptions!$B$14 | G38: =G12*Assumptions!$B$14 | H38: =H12*Assumptions!$B$14 | I38: =I12*Assumptions!$B$14
A39: Total current assets | C39: =SUM(C34:C38) | D39: =SUM(D34:D38) | E39: =SUM(E34:E38) | F39: =SUM(F34:F38) | G39: =SUM(G34:G38) | H39: =SUM(H34:H38) | I39: =SUM(I34:I38)
A40: Property and equipment, net | C40: 53.194 | D40: 83.83 | E40: =D40-E78-E12*Assumptions!E28 | F40: =E40-F78-F12*Assumptions!F28 | G40: =F40-G78-G12*Assumptions!G28 | H40: =G40-H78-H12*Assumptions!H28 | I40: =H40-I78-I12*Assumptions!I28
A41: Deferred commissions, noncurrent | C41: 132.465 | D41: 157.592 | E41: =E12*Assumptions!$B$13 | F41: =F12*Assumptions!$B$13 | G41: =G12*Assumptions!$B$13 | H41: =H12*Assumptions!$B$13 | I41: =I12*Assumptions!$B$13
A42: Goodwill | C42: 100.343 | D42: 199.606 | E42: =D42+Assumptions!E33 | F42: =E42+Assumptions!F33 | G42: =F42+Assumptions!G33 | H42: =G42+Assumptions!H33 | I42: =H42+Assumptions!I33
A43: Other assets, noncurrent (incl. intangibles) | C43: 59.331 | D43: 101.944 | E43: =D43-Assumptions!E29 | F43: =E43-Assumptions!F29 | G43: =F43-Assumptions!G29 | H43: =G43-Assumptions!H29 | I43: =H43-Assumptions!I29
A44: Total assets | C44: =C39+SUM(C40:C43) | D44: =D39+SUM(D40:D43) | E44: =E39+SUM(E40:E43) | F44: =F39+SUM(F40:F43) | G44: =G39+SUM(G40:G43) | H44: =H39+SUM(H40:H43) | I44: =I39+SUM(I40:I43)
A46: Accounts payable | C46: 10.439 | D46: 15.329 | E46: =E12*Assumptions!$B$15 | F46: =F12*Assumptions!$B$15 | G46: =G12*Assumptions!$B$15 | H46: =H12*Assumptions!$B$15 | I46: =I12*Assumptions!$B$15
A47: Accrued expenses and other current liabilities | C47: 162.602 | D47: 229.976 | E47: =E12*Assumptions!$B$16 | F47: =F12*Assumptions!$B$16 | G47: =G12*Assumptions!$B$16 | H47: =H12*Assumptions!$B$16 | I47: =I12*Assumptions!$B$16
A48: Deferred revenue, current | C48: 777.135 | D48: 1068.754 | E48: =E12*Assumptions!E32*Assumptions!$B$17 | F48: =F12*Assumptions!F32*Assumptions!$B$17 | G48: =G12*Assumptions!G32*Assumptions!$B$17 | H48: =H12*Assumptions!H32*Assumptions!$B$17 | I48: =I12*Assumptions!I32*Assumptions!$B$17
A49: Total current liabilities | C49: =SUM(C46:C48) | D49: =SUM(D46:D48) | E49: =SUM(E46:E48) | F49: =SUM(F46:F48) | G49: =SUM(G46:G48) | H49: =SUM(H46:H48) | I49: =SUM(I46:I48)
A50: Deferred revenue, noncurrent | C50: 642.37 | D50: 776.547 | E50: =E12*Assumptions!E32*(1-Assumptions!$B$17) | F50: =F12*Assumptions!F32*(1-Assumptions!$B$17) | G50: =G12*Assumptions!G32*(1-Assumptions!$B$17) | H50: =H12*Assumptions!H32*(1-Assumptions!$B$17) | I50: =I12*Assumptions!I32*(1-Assumptions!$B$17)
A51: Other liabilities, noncurrent | C51: 61.821 | D51: 64.771 | E51: =D51 | F51: =E51 | G51: =F51 | H51: =G51 | I51: =H51
A52: Convertible senior notes, net | C52: 0 | D52: 1130.721 | E52: =MIN(D52+Assumptions!$B$20,Assumptions!$B$19) | F52: =MIN(E52+Assumptions!$B$20,Assumptions!$B$19) | G52: =MIN(F52+Assumptions!$B$20,Assumptions!$B$19) | H52: =MIN(G52+Assumptions!$B$20,Assumptions!$B$19) | I52: =MIN(H52+Assumptions!$B$20,Assumptions!$B$19)
A53: Debt, noncurrent (term loan, repaid FY2026) | C53: 322.341 | D53: 0 | E53: =D53 | F53: =E53 | G53: =F53 | H53: =G53 | I53: =H53
A54: Total liabilities | C54: =C49+SUM(C50:C53) | D54: =D49+SUM(D50:D53) | E54: =E49+SUM(E50:E53) | F54: =F49+SUM(F50:F53) | G54: =G49+SUM(G50:G53) | H54: =H49+SUM(H50:H53) | I54: =I49+SUM(I50:I53)
A56: Common stock, par value | C56: 0.005 | D56: 0.005 | E56: =D56 | F56: =E56 | G56: =F56 | H56: =G56 | I56: =H56
A57: Additional paid-in capital | C57: 2291.829 | D57: 2662.861 | E57: =D57+E29 | F57: =E57+F29 | G57: =F57+G29 | H57: =G57+H29 | I57: =H57+I29
A58: Accumulated other comprehensive income (loss) | C58: -8.235 | D58: 3.733 | E58: =D58 | F58: =E58 | G58: =F58 | H58: =G58 | I58: =H58
A59: Accumulated deficit | C59: -2837.333 | D59: -3186.161 | E59: =D59+E28 | F59: =E59+F28 | G59: =F59+G28 | H59: =G59+H28 | I59: =H59+I28
A60: Total stockholders' equity (deficit) | C60: =SUM(C56:C59) | D60: =SUM(D56:D59) | E60: =SUM(E56:E59) | F60: =SUM(F56:F59) | G60: =SUM(G56:G59) | H60: =SUM(H56:H59) | I60: =SUM(I56:I59)
A61: Total liabilities and equity | C61: =C54+C60 | D61: =D54+D60 | E61: =E54+E60 | F61: =F54+F60 | G61: =G54+G60 | H61: =H54+H60 | I61: =I54+I60
A62: Balance check: assets minus liabilities and equity (must be zero) | C62: =ROUND(C44-C61,3) | D62: =ROUND(D44-D61,3) | E62: =ROUND(E44-E61,3) | F62: =ROUND(F44-F61,3) | G62: =ROUND(G44-G61,3) | H62: =ROUND(H44-H61,3) | I62: =ROUND(I44-I61,3)
A64: CASH FLOW STATEMENT
A65: Net income | B65: =B28 | C65: =C28 | D65: =D28 | E65: =E28 | F65: =F28 | G65: =G28 | H65: =H28 | I65: =I28
A66: Depreciation and amortisation | B66: =B30 | C66: =C30 | D66: =D30 | E66: =E30 | F66: =F30 | G66: =G30 | H66: =H30 | I66: =I30
A67: Stock-based compensation | B67: =B29 | C67: =C29 | D67: =D29 | E67: =E29 | F67: =F29 | G67: =G29 | H67: =H29 | I67: =I29
A68: Non-cash interest (note accretion) | B68: 10.117 | C68: 34.256 | D68: 0 | E68: =E52-D52 | F68: =F52-E52 | G68: =G52-F52 | H68: =H52-G52 | I68: =I52-H52
A69: Other non-cash items | B69: -0.899 | C69: -6.008 | D69: 7.119 | E69: 0 | F69: 0 | G69: 0 | H69: 0 | I69: 0
A70: Change in accounts receivable | B70: 17.157 | C70: -44.255 | D70: -79.786 | E70: =-(E36-D36) | F70: =-(F36-E36) | G70: =-(G36-F36) | H70: =-(H36-G36) | I70: =-(I36-H36)
A71: Change in deferred commissions (net of amortisation) | B71: -30.618 | C71: -38.513 | D71: -43.859 | E71: =-((E37+E41)-(D37+D41)) | F71: =-((F37+F41)-(E37+E41)) | G71: =-((G37+G41)-(F37+F41)) | H71: =-((H37+H41)-(G37+G41)) | I71: =-((I37+I41)-(H37+H41))
A72: Change in prepaid and other assets | B72: 2.251 | C72: -48.818 | D72: -111.727 | E72: =-(E38-D38) | F72: =-(F38-E38) | G72: =-(G38-F38) | H72: =-(H38-G38) | I72: =-(I38-H38)
A73: Change in accounts payable | B73: -1.012 | C73: 4.479 | D73: 4.479 | E73: =E46-D46 | F73: =F46-E46 | G73: =G46-F46 | H73: =H46-G46 | I73: =I46-H46
A74: Change in accrued and other liabilities | B74: 22.872 | C74: 45.882 | D74: 63.225 | E74: =(E47-D47)+(E51-D51) | F74: =(F47-E47)+(F51-E51) | G74: =(G47-F47)+(G51-F51) | H74: =(H47-G47)+(H51-G51) | I74: =(I47-H47)+(I51-H51)
A75: Change in deferred revenue | B75: 299.752 | C75: 313.244 | D75: 425.796 | E75: =(E48+E50)-(D48+D50) | F75: =(F48+F50)-(E48+E50) | G75: =(G48+G50)-(F48+F50) | H75: =(H48+H50)-(G48+G50) | I75: =(I48+I50)-(H48+H50)
A76: Cash from operating activities | B76: =SUM(B65:B75) | C76: =SUM(C65:C75) | D76: =SUM(D65:D75) | E76: =SUM(E65:E75) | F76: =SUM(F65:F75) | G76: =SUM(G65:G75) | H76: =SUM(H65:H75) | I76: =SUM(I65:I75)
A78: Capex incl. capitalised software | B78: -20.008 | C78: -26.599 | D78: -45.068 | E78: =-E12*Assumptions!E30 | F78: =-F12*Assumptions!F30 | G78: =-G12*Assumptions!G30 | H78: =-H12*Assumptions!H30 | I78: =-I12*Assumptions!I30
A79: Acquisitions | B79: -90.328 | C79: 0 | D79: -21.259 | E79: =-Assumptions!E33 | F79: =-Assumptions!F33 | G79: =-Assumptions!G33 | H79: =-Assumptions!H33 | I79: =-Assumptions!I33
A80: Net (purchases) / maturities of investments | B80: 16.713 | C80: -356.843 | D80: -763.762 | E80: =-(E35-D35) | F80: =-(F35-E35) | G80: =-(G35-F35) | H80: =-(H35-G35) | I80: =-(I35-H35)
A81: Cash from investing activities | B81: =SUM(B78:B80) | C81: =SUM(C78:C80) | D81: =SUM(D78:D80) | E81: =SUM(E78:E80) | F81: =SUM(F78:F80) | G81: =SUM(G78:G80) | H81: =SUM(H78:H80) | I81: =SUM(I78:I80)
A83: Cash from financing activities | B83: 95.949 | C83: 398.023 | D83: 736.501 | E83: 0 | F83: 0 | G83: 0 | H83: 0 | I83: 0
A84: Effect of exchange rates | B84: -1.355 | C84: -6.274 | D84: 9.826 | E84: 0 | F84: 0 | G84: 0 | H84: 0 | I84: 0
A85: Net change in cash | B85: =B76+B81+B83+B84 | C85: =C76+C81+C83+C84 | D85: =D76+D81+D83+D84 | E85: =E76+E81+E83+E84 | F85: =F76+F81+F83+F84 | G85: =G76+G81+G83+G84 | H85: =H76+H81+H83+H84 | I85: =I76+I81+I83+I84
A86: Opening cash | B86: 140.606 | C86: 137.059 | D86: 193.594 | E86: =D34 | F86: =E34 | G86: =F34 | H86: =G34 | I86: =H34
A87: Closing cash | B87: =B86+B85 | C87: =C86+C85 | D87: =D86+D85 | E87: =E86+E85 | F87: =F86+F85 | G87: =G86+G85 | H87: =H86+H85 | I87: =I86+I85
A88: Historical opening and closing cash include restricted cash (about $12.5m at FY2026); projected cash equals balance sheet cash.
A90: Free cash flow (operating cash flow less capex) | B90: =B76+B78 | C90: =C76+C78 | D90: =D76+D78 | E90: =E76+E78 | F90: =F76+F78 | G90: =G76+G78 | H90: =H76+H78 | I90: =I76+I78
A91: Free cash flow margin | B91: =B90/B12 | C91: =C90/C12 | D91: =D90/D12 | E91: =E90/E12 | F91: =F90/F12 | G91: =G90/G12 | H91: =H90/H12 | I91: =I90/I12

Sheet DCF
A1: Rubrik (RBRK): discounted cash flow
A2: $ millions. Valuation date 31 Jan 2026. End-of-year discounting. SBC treated as an operating cost (not added back).
C3: FY2027E | D3: FY2028E | E3: FY2029E | F3: FY2030E | G3: FY2031E | H3: FY2032E | I3: FY2033E | J3: FY2034E | K3: FY2035E | L3: FY2036E
A4: Stage | C4: Explicit | D4: Explicit | E4: Explicit | F4: Explicit | G4: Explicit | H4: Fade | I4: Fade | J4: Fade | K4: Fade | L4: Fade
A5: Year (t) | C5: 1 | D5: 2 | E5: 3 | F5: 4 | G5: 5 | H5: 6 | I5: 7 | J5: 8 | K5: 9 | L5: 10
A6: Revenue | C6: =Model!E12 | D6: =Model!F12 | E6: =Model!G12 | F6: =Model!H12 | G6: =Model!I12 | H6: =G6*(1+H7) | I6: =H6*(1+I7) | J6: =I6*(1+J7) | K6: =J6*(1+K7) | L6: =K6*(1+L7)
A7: Revenue growth | C7: =Model!E13 | D7: =Model!F13 | E7: =Model!G13 | F7: =Model!H13 | G7: =Model!I13 | H7: =$G$7-($G$7-Assumptions!$B$48)*(H$5-5)/5 | I7: =$G$7-($G$7-Assumptions!$B$48)*(I$5-5)/5 | J7: =$G$7-($G$7-Assumptions!$B$48)*(J$5-5)/5 | K7: =$G$7-($G$7-Assumptions!$B$48)*(K$5-5)/5 | L7: =$G$7-($G$7-Assumptions!$B$48)*(L$5-5)/5
A8: EBIT (after SBC) | C8: =Model!E21 | D8: =Model!F21 | E8: =Model!G21 | F8: =Model!H21 | G8: =Model!I21
A9: Less: cash taxes | C9: =-Model!E27 | D9: =-Model!F27 | E9: =-Model!G27 | F9: =-Model!H27 | G9: =-Model!I27
A10: Plus: depreciation and amortisation | C10: =Model!E30 | D10: =Model!F30 | E10: =Model!G30 | F10: =Model!H30 | G10: =Model!I30
A11: Less: capex | C11: =Model!E78 | D11: =Model!F78 | E11: =Model!G78 | F11: =Model!H78 | G11: =Model!I78
A12: Plus / (less): change in net working capital | C12: =SUM(Model!E70:E75) | D12: =SUM(Model!F70:F75) | E12: =SUM(Model!G70:G75) | F12: =SUM(Model!H70:H75) | G12: =SUM(Model!I70:I75)
A13: Unlevered free cash flow | C13: =SUM(C8:C12) | D13: =SUM(D8:D12) | E13: =SUM(E8:E12) | F13: =SUM(F8:F12) | G13: =SUM(G8:G12) | H13: =H6*H14 | I13: =I6*I14 | J13: =J6*J14 | K13: =K6*K14 | L13: =L6*L14
A14: UFCF margin | C14: =C13/C6 | D14: =D13/D6 | E14: =E13/E6 | F14: =F13/F6 | G14: =G13/G6 | H14: =$G$14+(Assumptions!$B$49-$G$14)*(H$5-5)/5 | I14: =$G$14+(Assumptions!$B$49-$G$14)*(I$5-5)/5 | J14: =$G$14+(Assumptions!$B$49-$G$14)*(J$5-5)/5 | K14: =$G$14+(Assumptions!$B$49-$G$14)*(K$5-5)/5 | L14: =$G$14+(Assumptions!$B$49-$G$14)*(L$5-5)/5
A15: Memo: stock-based compensation | C15: =Model!E29 | D15: =Model!F29 | E15: =Model!G29 | F15: =Model!H29 | G15: =Model!I29
A16: Memo: UFCF if SBC were added back | C16: =C13+C15 | D16: =D13+D15 | E16: =E13+E15 | F16: =F13+F15 | G16: =G13+G15
A17: Discount factor | C17: =1/(1+Assumptions!$B$47)^C5 | D17: =1/(1+Assumptions!$B$47)^D5 | E17: =1/(1+Assumptions!$B$47)^E5 | F17: =1/(1+Assumptions!$B$47)^F5 | G17: =1/(1+Assumptions!$B$47)^G5 | H17: =1/(1+Assumptions!$B$47)^H5 | I17: =1/(1+Assumptions!$B$47)^I5 | J17: =1/(1+Assumptions!$B$47)^J5 | ... L17: =1/(1+Assumptions!$B$47)^L5
A18: Present value of UFCF | C18: =C13*C17 | D18: =D13*D17 | E18: =E13*E17 | F18: =F13*F17 | G18: =G13*G17 | H18: =H13*H17 | I18: =I13*I17 | J18: =J13*J17 | ... L18: =L13*L17
A20: VALUATION
A21: Sum of PV of UFCF, FY2027E to FY2036E | C21: =SUM(C18:L18)
A22: Terminal-year UFCF (FY2037) | C22: =L13*(1+Assumptions!B48)
A23: Terminal value at end of FY2036 | C23: =C22/(Assumptions!B47-Assumptions!B48)
A24: PV of terminal value | C24: =C23*L17
A25: Enterprise value | C25: =C21+C24
A26: Terminal value as % of enterprise value | C26: =C24/C25
A27: Plus: cash and short-term investments (31 Jan 2026) | C27: =Model!D34+Model!D35
A28: Less: convertible notes at face | C28: =Assumptions!B19
A29: Equity value | C29: =C25+C27-C28
A30: Diluted shares excluding convertible (m) | C30: =Assumptions!B50
A31: Implied value per share at 31 Jan 2026 ($) | C31: =C29/C30
A32: Rolled forward to today at the cost of equity ($) | C32: =C31*(1+Assumptions!B40)^Assumptions!B51
A33: Current share price ($) | C33: =Assumptions!B43
A34: Implied upside / (downside) | C34: =C32/C33-1
A36: SENSITIVITY: implied value per share at valuation date ($)
A37: Holds the UFCF path fixed and varies the discount rate and the perpetuity growth used in the terminal value.
B38: WACC \ g | C38: 0.03 | D38: 0.035 | E38: 0.04 | F38: 0.045 | G38: 0.05
B39: 0.075 | C39: =(SUMPRODUCT($C$13:$L$13,1/(1+$B39)^$C$5:$L$5)+$L$13*(1+C$38)/($B39-C$38)/(1+$B39)^10+$C$27-$C$28)/$C$30 | D39: =(SUMPRODUCT($C$13:$L$13,1/(1+$B39)^$C$5:$L$5)+$L$13*(1+D$38)/($B39-D$38)/(1+$B39)^10+$C$27-$C$28)/$C$30 | E39: =(SUMPRODUCT($C$13:$L$13,1/(1+$B39)^$C$5:$L$5)+$L$13*(1+E$38)/($B39-E$38)/(1+$B39)^10+$C$27-$C$28)/$C$30 | F39: =(SUMPRODUCT($C$13:$L$13,1/(1+$B39)^$C$5:$L$5)+$L$13*(1+F$38)/($B39-F$38)/(1+$B39)^10+$C$27-$C$28)/$C$30 | G39: =(SUMPRODUCT($C$13:$L$13,1/(1+$B39)^$C$5:$L$5)+$L$13*(1+G$38)/($B39-G$38)/(1+$B39)^10+$C$27-$C$28)/$C$30
B40: 0.08 | C40: =(SUMPRODUCT($C$13:$L$13,1/(1+$B40)^$C$5:$L$5)+$L$13*(1+C$38)/($B40-C$38)/(1+$B40)^10+$C$27-$C$28)/$C$30 | D40: =(SUMPRODUCT($C$13:$L$13,1/(1+$B40)^$C$5:$L$5)+$L$13*(1+D$38)/($B40-D$38)/(1+$B40)^10+$C$27-$C$28)/$C$30 | E40: =(SUMPRODUCT($C$13:$L$13,1/(1+$B40)^$C$5:$L$5)+$L$13*(1+E$38)/($B40-E$38)/(1+$B40)^10+$C$27-$C$28)/$C$30 | F40: =(SUMPRODUCT($C$13:$L$13,1/(1+$B40)^$C$5:$L$5)+$L$13*(1+F$38)/($B40-F$38)/(1+$B40)^10+$C$27-$C$28)/$C$30 | G40: =(SUMPRODUCT($C$13:$L$13,1/(1+$B40)^$C$5:$L$5)+$L$13*(1+G$38)/($B40-G$38)/(1+$B40)^10+$C$27-$C$28)/$C$30
B41: 0.085 | C41: =(SUMPRODUCT($C$13:$L$13,1/(1+$B41)^$C$5:$L$5)+$L$13*(1+C$38)/($B41-C$38)/(1+$B41)^10+$C$27-$C$28)/$C$30 | D41: =(SUMPRODUCT($C$13:$L$13,1/(1+$B41)^$C$5:$L$5)+$L$13*(1+D$38)/($B41-D$38)/(1+$B41)^10+$C$27-$C$28)/$C$30 | E41: =(SUMPRODUCT($C$13:$L$13,1/(1+$B41)^$C$5:$L$5)+$L$13*(1+E$38)/($B41-E$38)/(1+$B41)^10+$C$27-$C$28)/$C$30 | F41: =(SUMPRODUCT($C$13:$L$13,1/(1+$B41)^$C$5:$L$5)+$L$13*(1+F$38)/($B41-F$38)/(1+$B41)^10+$C$27-$C$28)/$C$30 | G41: =(SUMPRODUCT($C$13:$L$13,1/(1+$B41)^$C$5:$L$5)+$L$13*(1+G$38)/($B41-G$38)/(1+$B41)^10+$C$27-$C$28)/$C$30
B42: 0.09 | C42: =(SUMPRODUCT($C$13:$L$13,1/(1+$B42)^$C$5:$L$5)+$L$13*(1+C$38)/($B42-C$38)/(1+$B42)^10+$C$27-$C$28)/$C$30 | D42: =(SUMPRODUCT($C$13:$L$13,1/(1+$B42)^$C$5:$L$5)+$L$13*(1+D$38)/($B42-D$38)/(1+$B42)^10+$C$27-$C$28)/$C$30 | E42: =(SUMPRODUCT($C$13:$L$13,1/(1+$B42)^$C$5:$L$5)+$L$13*(1+E$38)/($B42-E$38)/(1+$B42)^10+$C$27-$C$28)/$C$30 | F42: =(SUMPRODUCT($C$13:$L$13,1/(1+$B42)^$C$5:$L$5)+$L$13*(1+F$38)/($B42-F$38)/(1+$B42)^10+$C$27-$C$28)/$C$30 | G42: =(SUMPRODUCT($C$13:$L$13,1/(1+$B42)^$C$5:$L$5)+$L$13*(1+G$38)/($B42-G$38)/(1+$B42)^10+$C$27-$C$28)/$C$30
B43: 0.095 | C43: =(SUMPRODUCT($C$13:$L$13,1/(1+$B43)^$C$5:$L$5)+$L$13*(1+C$38)/($B43-C$38)/(1+$B43)^10+$C$27-$C$28)/$C$30 | D43: =(SUMPRODUCT($C$13:$L$13,1/(1+$B43)^$C$5:$L$5)+$L$13*(1+D$38)/($B43-D$38)/(1+$B43)^10+$C$27-$C$28)/$C$30 | E43: =(SUMPRODUCT($C$13:$L$13,1/(1+$B43)^$C$5:$L$5)+$L$13*(1+E$38)/($B43-E$38)/(1+$B43)^10+$C$27-$C$28)/$C$30 | F43: =(SUMPRODUCT($C$13:$L$13,1/(1+$B43)^$C$5:$L$5)+$L$13*(1+F$38)/($B43-F$38)/(1+$B43)^10+$C$27-$C$28)/$C$30 | G43: =(SUMPRODUCT($C$13:$L$13,1/(1+$B43)^$C$5:$L$5)+$L$13*(1+G$38)/($B43-G$38)/(1+$B43)^10+$C$27-$C$28)/$C$30
B44: 0.1 | C44: =(SUMPRODUCT($C$13:$L$13,1/(1+$B44)^$C$5:$L$5)+$L$13*(1+C$38)/($B44-C$38)/(1+$B44)^10+$C$27-$C$28)/$C$30 | D44: =(SUMPRODUCT($C$13:$L$13,1/(1+$B44)^$C$5:$L$5)+$L$13*(1+D$38)/($B44-D$38)/(1+$B44)^10+$C$27-$C$28)/$C$30 | E44: =(SUMPRODUCT($C$13:$L$13,1/(1+$B44)^$C$5:$L$5)+$L$13*(1+E$38)/($B44-E$38)/(1+$B44)^10+$C$27-$C$28)/$C$30 | F44: =(SUMPRODUCT($C$13:$L$13,1/(1+$B44)^$C$5:$L$5)+$L$13*(1+F$38)/($B44-F$38)/(1+$B44)^10+$C$27-$C$28)/$C$30 | G44: =(SUMPRODUCT($C$13:$L$13,1/(1+$B44)^$C$5:$L$5)+$L$13*(1+G$38)/($B44-G$38)/(1+$B44)^10+$C$27-$C$28)/$C$30
B45: 0.105 | C45: =(SUMPRODUCT($C$13:$L$13,1/(1+$B45)^$C$5:$L$5)+$L$13*(1+C$38)/($B45-C$38)/(1+$B45)^10+$C$27-$C$28)/$C$30 | D45: =(SUMPRODUCT($C$13:$L$13,1/(1+$B45)^$C$5:$L$5)+$L$13*(1+D$38)/($B45-D$38)/(1+$B45)^10+$C$27-$C$28)/$C$30 | E45: =(SUMPRODUCT($C$13:$L$13,1/(1+$B45)^$C$5:$L$5)+$L$13*(1+E$38)/($B45-E$38)/(1+$B45)^10+$C$27-$C$28)/$C$30 | F45: =(SUMPRODUCT($C$13:$L$13,1/(1+$B45)^$C$5:$L$5)+$L$13*(1+F$38)/($B45-F$38)/(1+$B45)^10+$C$27-$C$28)/$C$30 | G45: =(SUMPRODUCT($C$13:$L$13,1/(1+$B45)^$C$5:$L$5)+$L$13*(1+G$38)/($B45-G$38)/(1+$B45)^10+$C$27-$C$28)/$C$30
B46: 0.11 | C46: =(SUMPRODUCT($C$13:$L$13,1/(1+$B46)^$C$5:$L$5)+$L$13*(1+C$38)/($B46-C$38)/(1+$B46)^10+$C$27-$C$28)/$C$30 | D46: =(SUMPRODUCT($C$13:$L$13,1/(1+$B46)^$C$5:$L$5)+$L$13*(1+D$38)/($B46-D$38)/(1+$B46)^10+$C$27-$C$28)/$C$30 | E46: =(SUMPRODUCT($C$13:$L$13,1/(1+$B46)^$C$5:$L$5)+$L$13*(1+E$38)/($B46-E$38)/(1+$B46)^10+$C$27-$C$28)/$C$30 | F46: =(SUMPRODUCT($C$13:$L$13,1/(1+$B46)^$C$5:$L$5)+$L$13*(1+F$38)/($B46-F$38)/(1+$B46)^10+$C$27-$C$28)/$C$30 | G46: =(SUMPRODUCT($C$13:$L$13,1/(1+$B46)^$C$5:$L$5)+$L$13*(1+G$38)/($B46-G$38)/(1+$B46)^10+$C$27-$C$28)/$C$30
A47: Value per share added if SBC were treated as non-cash in FY2027E to FY2031E only ($) | C47: =SUMPRODUCT(C15:G15,C17:G17)/C30
A48: Shows how much of a DCF value can come from one accounting choice. Not used in the base case.
A50: MARKET-IMPLIED ASSUMPTION
A51: Value per share today is linear in the steady-state UFCF margin: value = A + B x margin. Solving for the margin that returns the current share price.
A52: A: value per share today with a zero steady-state margin ($) | C52: =(SUMPRODUCT(C13:G13,C17:G17)+SUMPRODUCT(H6:L6*(1-(H5:L5-5)/5)*H17:L17)*$G$14+C27-C28)/C30*(1+Assumptions!B40)^Assumptions!B51
A53: B: value per share added per 100% of steady-state margin ($) | C53: =(SUMPRODUCT(H6:L6*(H5:L5-5)/5*H17:L17)+L6*(1+Assumptions!B48)/(Assumptions!B47-Assumptions!B48)*L17)/C30*(1+Assumptions!B40)^Assumptions!B51
A54: Check: A + B x base-case margin equals the rolled-forward value above | C54: =IF(ABS(C52+C53*Assumptions!B49-C32)<0.01,"PASS","CHECK")
A55: Steady-state UFCF margin implied by the current share price | C55: =(C33-C52)/C53
A56: Compare with the base case (Assumptions B49). Same WACC, terminal growth and FY2027E to FY2031E cash flows.

Sheet Reconciliation
A1: Reconciliation: sector report revenue projection to this model
A2: $ millions. Each column changes one input from the column to its left. Same growth-decay method throughout; only the inputs differ.
C3: A. Sector model as first built | D3: B. Filed FY2026 exit ARR | E3: C. k from filed ARR (corrected sector model) | F3: D. August 2026 guidance | G3: E. Revenue / ARR 1.00 from FY2028 (this model)
A4: What changed | C4: Rounded inputs ($1,460m, k 0.77) | D4: $1,462.1m from the Q4 FY2026 release | E4: 16.70pp / 22.24pp = 0.75 | F4: Q2 FY2027 release: ARR $1,882.5m, revenue $1,689m | G4: Material rights treated as exhausted after FY2027
A6: Inputs
A7: FY2026 exit subscription ARR | C7: 1460 | D7: 1462.092 | E7: 1462.092 | F7: =Model!D6 | G7: =Model!D6
A8: FY2027 exit subscription ARR | C8: 1834 | D8: 1834 | E8: 1834 | F8: =Assumptions!B6 | G8: =Assumptions!B6
A9: FY2027 revenue | C9: 1602 | D9: 1602 | E9: 1602 | F9: =Assumptions!B7 | G9: =Assumptions!B7
A10: Decay factor k | C10: 0.77 | D10: 0.77 | E10: 0.75 | F10: =Assumptions!B9 | G10: =Assumptions!B9
A11: Revenue / average ARR, FY2028 onward | C11: 0.97 | D11: 0.97 | E11: 0.97 | F11: 0.97 | G11: =Assumptions!B10
A12: Market growth (decay floor) | C12: =Assumptions!B8 | D12: =Assumptions!B8 | E12: =Assumptions!B8 | F12: =Assumptions!B8 | G12: =Assumptions!B8
A14: Projection
A15: FY2027 ARR growth | C15: =C8/C7-1 | D15: =D8/D7-1 | E15: =E8/E7-1 | F15: =F8/F7-1 | G15: =G8/G7-1
A16: FY2028 ARR growth | C16: =C12+(C15-C12)*C10 | D16: =D12+(D15-D12)*D10 | E16: =E12+(E15-E12)*E10 | F16: =F12+(F15-F12)*F10 | G16: =G12+(G15-G12)*G10
A17: FY2029 ARR growth | C17: =C12+(C15-C12)*C10^2 | D17: =D12+(D15-D12)*D10^2 | E17: =E12+(E15-E12)*E10^2 | F17: =F12+(F15-F12)*F10^2 | G17: =G12+(G15-G12)*G10^2
A18: FY2030 ARR growth | C18: =C12+(C15-C12)*C10^3 | D18: =D12+(D15-D12)*D10^3 | E18: =E12+(E15-E12)*E10^3 | F18: =F12+(F15-F12)*F10^3 | G18: =G12+(G15-G12)*G10^3
A19: FY2028 exit ARR | C19: =C8*(1+C16) | D19: =D8*(1+D16) | E19: =E8*(1+E16) | F19: =F8*(1+F16) | G19: =G8*(1+G16)
A20: FY2029 exit ARR | C20: =C19*(1+C17) | D20: =D19*(1+D17) | E20: =E19*(1+E17) | F20: =F19*(1+F17) | G20: =G19*(1+G17)
A21: FY2030 exit ARR | C21: =C20*(1+C18) | D21: =D20*(1+D18) | E21: =E20*(1+E18) | F21: =F20*(1+F18) | G21: =G20*(1+G18)
A22: FY2028 revenue | C22: =C11*(C8+C19)/2 | D22: =D11*(D8+D19)/2 | E22: =E11*(E8+E19)/2 | F22: =F11*(F8+F19)/2 | G22: =G11*(G8+G19)/2
A23: FY2029 revenue | C23: =C11*(C19+C20)/2 | D23: =D11*(D19+D20)/2 | E23: =E11*(E19+E20)/2 | F23: =F11*(F19+F20)/2 | G23: =G11*(G19+G20)/2
A24: FY2030 revenue | C24: =C11*(C20+C21)/2 | D24: =D11*(D20+D21)/2 | E24: =E11*(E20+E21)/2 | F24: =F11*(F20+F21)/2 | G24: =G11*(G20+G21)/2
A25: Three-year revenue CAGR, FY2027 to FY2030 | C25: =(C24/C9)^(1/3)-1 | D25: =(D24/D9)^(1/3)-1 | E25: =(E24/E9)^(1/3)-1 | F25: =(F24/F9)^(1/3)-1 | G25: =(G24/G9)^(1/3)-1
A27: Change from previous column
A28: FY2030 revenue ($m) | D28: =D24-C24 | E28: =E24-D24 | F28: =F24-E24 | G28: =G24-F24
A29: Three-year CAGR (percentage points) | D29: =(D25-C25)*100 | E29: =(E25-D25)*100 | F29: =(F25-E25)*100 | G29: =(G25-F25)*100
A31: Ties
A32: Scenario C equals revenue-projection-model.xlsx, Rubrik!E8 | B32: 2948.555 | C32: =IF(ABS(E24-B32)<0.01,"PASS","CHECK")
A33: Scenario E equals Model FY2030E revenue | B33: =Model!H12 | C33: =IF(ABS(G24-B33)<0.01,"PASS","CHECK")
A35: The submitted sector report PDF shows FY2028 to FY2030 revenue of 1,996 / 2,451 / 2,978 and a 22.9% CAGR. They match the unrounded FY2027 ratio (about 0.973) to within $1m, although the report states 0.97. Scenario A is the spreadsheet as first built.

Sheet Checks
A1: Integrity and validation checks
A3: Check | B3: Model value | C3: Target | D3: Result
A4: Balance sheet balances, all years (max absolute difference) | B4: =MAX(ABS(Model!C62),ABS(Model!D62),ABS(Model!E62),ABS(Model!F62),ABS(Model!G62),ABS(Model!H62),ABS(Model!I62)) | C4: 0 | D4: =IF(B4<0.001,"PASS","CHECK")
A5: FY2026 net income ties to 10-K | B5: =Model!D28 | C5: -348.828 | D5: =IF(ABS(B5-C5)<0.001,"PASS","CHECK")
A6: FY2026 cash from operations ties to 10-K | B6: =Model!D76 | C6: 282.908 | D6: =IF(ABS(B6-C6)<0.001,"PASS","CHECK")
A7: FY2026 free cash flow ties to earnings release | B7: =Model!D90 | C7: 237.84 | D7: =IF(ABS(B7-C7)<0.001,"PASS","CHECK")
A8: FY2026 total assets ties to 10-K | B8: =Model!D44 | C8: 2766.536 | D8: =IF(ABS(B8-C8)<0.001,"PASS","CHECK")
A9: FY2026 closing cash incl. restricted ties to 10-K | B9: =Model!D87 | C9: 392.74 | D9: =IF(ABS(B9-C9)<0.001,"PASS","CHECK")
A10: FY2027 revenue equals guidance midpoint | B10: =Model!E12 | C10: 1689 | D10: =IF(ABS(B10-C10)<0.001,"PASS","CHECK")
A11: FY2027 exit ARR equals guidance midpoint | B11: =Model!E6 | C11: 1882.5 | D11: =IF(ABS(B11-C11)<0.001,"PASS","CHECK")
A12: FY2027 free cash flow within guidance ($323m to $333m) | B12: =Model!E90 | C12: 323 to 333 | D12: =IF(AND(B12>=323,B12<=333),"IN RANGE","OUTSIDE")
A13: Terminal growth below WACC | B13: =Assumptions!B48 | C13: =Assumptions!B47 | D13: =IF(B13<C13,"PASS","FAIL")
A14: Reconciliation bridge ends at Model FY2030E revenue | B14: =Reconciliation!G24 | C14: =Model!H12 | D14: =IF(ABS(B14-C14)<0.001,"PASS","CHECK")
A15: Context (not pass/fail)
A16: FY2027E operating margin vs H1 FY2027 actual | B16: =Model!E22 | C16: -0.1529 | D16: H1 FY2027: operating loss $124.5m on revenue $814.3m
A17: Note: the FY2027 deferred revenue ratio is set so modelled FCF matches the guidance midpoint. Row 12 is a calibration, not an independent test.
A19: BACKTEST: would holding FY2025 working-capital ratios have predicted FY2026 cash flow?
A20: Uses actual FY2026 revenue and FY2025 balance-sheet ratios; compares the implied working-capital cash effect with what Rubrik reported.
A21: FY2025 receivables / revenue | B21: =Model!C36/Model!C12
A22: FY2025 deferred commissions / revenue | B22: =(Model!C37+Model!C41)/Model!C12
A23: FY2025 prepaid / revenue | B23: =Model!C38/Model!C12
A24: FY2025 payables / revenue | B24: =Model!C46/Model!C12
A25: FY2025 accrued / revenue | B25: =Model!C47/Model!C12
A26: FY2025 deferred revenue / revenue | B26: =(Model!C48+Model!C50)/Model!C12
A27: Predicted FY2026 working-capital cash effect | B27: =-(B21*Model!D12-Model!C36)-(B22*Model!D12-(Model!C37+Model!C41))-(B23*Model!D12-Model!C38)+(B24*Model!D12-Model!C46)+(B25*Model!D12-Model!C47)+(B26*Model!D12-(Model!C48+Model!C50))
A28: Actual FY2026 working-capital cash effect | B28: =SUM(Model!D70:D75)
A29: Prediction error (predicted minus actual) | B29: =B27-B28
A30: of which: deferred revenue | B30: =(B26*Model!D12-(Model!C48+Model!C50))-Model!D75
A31: Holding the deferred revenue ratio flat would have overstated FY2026 operating cash flow by most of the error above. The ratio fell from 160% to 140%, so the projection steps it down rather than holding it.
A33: DCF market-implied margin solve reproduces the base value | D33: =DCF!C54
